powerbi_cli/__init__.py
powerbi_cli/admin/__init__.py
powerbi_cli/admin/main.py
powerbi_cli/auth/__init__.py
powerbi_cli/auth/main.py
powerbi_cli/auth/token.py
powerbi_cli/client.py
powerbi_cli/dataset/__init__.py
powerbi_cli/dataset/get.py
powerbi_cli/dataset/list.py
powerbi_cli/dataset/main.py
powerbi_cli/dataset/query.py
powerbi_cli/dataset/refresh/__init__.py
powerbi_cli/dataset/refresh/main.py
powerbi_cli/dataset/refresh/start.py
powerbi_cli/main.py
powerbi_cli/report/__init__.py
powerbi_cli/report/export.py
powerbi_cli/report/get.py
powerbi_cli/report/list.py
powerbi_cli/report/main.py
powerbi_cli/report/open.py
powerbi_cli/utils.py
powerbi_cli/workspace/__init__.py
powerbi_cli/workspace/get.py
powerbi_cli/workspace/list.py
powerbi_cli/workspace/main.py
powerbi_cli-0.2.0.dist-info/METADATA
powerbi_cli-0.2.0.dist-info/WHEEL
powerbi_cli-0.2.0.dist-info/entry_points.txt
powerbi_cli-0.2.0.dist-info/RECORD
